skigmachat/__init__.py
skigmachat-0.1.1.dist-info/LICENSE
skigmachat-0.1.1.dist-info/METADATA
skigmachat-0.1.1.dist-info/WHEEL
skigmachat-0.1.1.dist-info/top_level.txt
skigmachat-0.1.1.dist-info/RECORD
