Metadata-Version: 2.2
Name: skigmachat
Version: 0.1.1
Summary: Discord bot for chatroom.skigmanetwork.de
Home-page: https://github.com/Spigey/skigmachat
Author: Spigey
Author-email: ludwig@skigmanetwork.de
Classifier: Programming Language :: Python :: 3
Classifier: License :: OSI Approved :: MIT License
Classifier: Operating System :: OS Independent
License-File: LICENSE
Requires-Dist: websockets
Dynamic: author
Dynamic: author-email
Dynamic: classifier
Dynamic: description
Dynamic: description-content-type
Dynamic: home-page
Dynamic: requires-dist
Dynamic: summary
